bakemate
