Metadata-Version: 1.0
Name: bakemate
Version: 0.5
Summary: a baker helper
Home-page: https://github.com/tengu/py-bakemate
Author: karasuyamatengu
Author-email: karasuyamatengu@gmail.com
License: LGPL
Keywords: baker
Platform: UNKNOWN
Classifier: License :: OSI Approved :: GNU Library or Lesser General Public License (LGPL)
Classifier: Programming Language :: Python
Classifier: Development Status :: 4 - Beta
Classifier: Environment :: Console
Classifier: Intended Audience :: Developers
